valery/__init__.py
valery-0.0.1.dist-info/METADATA
valery-0.0.1.dist-info/WHEEL
valery-0.0.1.dist-info/top_level.txt
valery-0.0.1.dist-info/RECORD
