Metadata-Version: 2.1
Name: valery
Version: 0.0.1
Summary: Valery is a static site generator
Home-page: https://gitlab.com/13g10n/valery
Author: Ivan Borisenko
Author-email: mteru00@gmail.com
License: MIT
Platform: UNKNOWN
